gimmeshell/__init__.py
gimmeshell/shell.py
gimmeshell-0.0.0.dist-info/METADATA
gimmeshell-0.0.0.dist-info/WHEEL
gimmeshell-0.0.0.dist-info/entry_points.txt
gimmeshell-0.0.0.dist-info/top_level.txt
gimmeshell-0.0.0.dist-info/RECORD
